<?xml version="1.0" encoding="UTF-8" standalone="yes"?>
<node artifactManager="be.nabu.eai.module.types.structure.StructureManager" created="2024-01-19T19:02:43.574+01:00" lastModified="2025-01-22T11:10:55.671+01:00" leaf="true" version="27">
    <environmentId>ares</environmentId>
    <hidden>false</hidden>
    <locked>false</locked>
    <properties/>
    <references>java.util.UUID</references>
    <references>java.util.Date</references>
    <references>java.lang.String</references>
    <references>java.net.URI</references>
    <references>be.nabu.utils.cep.api.EventSeverity</references>
</node>
